lso/init.py
lso/lso.py
lso_python-0.0.2.dist-info/LICENSE
lso_python-0.0.2.dist-info/METADATA
lso_python-0.0.2.dist-info/WHEEL
lso_python-0.0.2.dist-info/top_level.txt
lso_python-0.0.2.dist-info/RECORD
