Metadata-Version: 2.1
Name: lso-python
Version: 0.0.2
Summary: Package to do Log Search
Author-email: Gaurav Mishra <gaurav.mishra@karza.in>
Project-URL: Homepage, https://github.com/seedhesaadheakshay/Log-Search-Optimization
Project-URL: Bug Tracker, https://github.com/seedhesaadheakshay/Log-Search-Optimization/issues
Classifier: Programming Language :: Python :: 3
Classifier: License :: OSI Approved :: MIT License
Classifier: Operating System :: OS Independent
Requires-Python: >=3.7
License-File: LICENSE
